TBuddy_SDK/__init__.py
TBuddy_SDK/auth.py
TBuddy_SDK/cache.py
TBuddy_SDK/client.py
TBuddy_SDK/config.py
TBuddy_SDK/exceptions.py
TBuddy_SDK/logger.py
TBuddy_SDK/metrics.py
TBuddy_SDK/models.py
TBuddy_SDK/rate_limiter.py
TBuddy_SDK/rest_client.py
TBuddy_SDK/retry.py
TBuddy_SDK/session_manager.py
TBuddy_SDK/websocket_client.py
tbuddy-2.0.0.dist-info/licenses/license
tbuddy-2.0.0.dist-info/METADATA
tbuddy-2.0.0.dist-info/WHEEL
tbuddy-2.0.0.dist-info/top_level.txt
tbuddy-2.0.0.dist-info/RECORD
