Metadata-Version: 2.4
Name: tbuddy
Version: 2.0.0
Summary: A Python client for MCP service
Author-email: Ayush Jadaun <ayusjadaun6@gmail.com>
License-Expression: MIT
Classifier: Programming Language :: Python :: 3
Classifier: Operating System :: OS Independent
Requires-Python: >=3.8
License-File: license
Requires-Dist: httpx>=0.24.0
Requires-Dist: websockets>=11.0
Requires-Dist: pydantic>=2.0
Requires-Dist: cachetools>=5.3
Dynamic: license-file
